gen_doc/__init__.py
gen_doc/commands.py
gen_doc/doc_generator.py
gen_doc/exc.py
gen_doc/settings.py
gen_doc/extensions/__init__.py
gen_doc/extensions/parser.py
gen_doc/extensions/python/__init__.py
gen_doc/extensions/python/python_parser.py
gen_doc/extensions/python/utils/__init__.py
gen_doc/extensions/python/utils/base_parser.py
gen_doc/extensions/python/utils/parser_doc_string.py
gen_doc/extensions/python/utils/parser_python_google_docstring.py
gen_doc/extensions/python/utils/parser_python_sphinx_docstring.py
gen_doc/extensions/python/utils/utils.py
gen_doc/models/__init__.py
gen_doc/models/folder_general_information.py
gen_doc/models/module.py
gen_doc/models/variables.py
gen_doc/serializers/__init__.py
gen_doc/serializers/serializer.py
gen_doc/serializers/markdown/__init__.py
gen_doc/serializers/markdown/markdown_serializer.py
gen_doc/src/template.yaml
gen_doc/utils/command_utils.py
gen_doc/utils/config_handler.py
gen_doc/utils/utils.py
gen_doc-0.1.3.dist-info/LICENSE
gen_doc-0.1.3.dist-info/METADATA
gen_doc-0.1.3.dist-info/WHEEL
gen_doc-0.1.3.dist-info/entry_points.txt
gen_doc-0.1.3.dist-info/top_level.txt
gen_doc-0.1.3.dist-info/RECORD
