Metadata-Version: 2.1
Name: gen-doc
Version: 0.1.3
Summary: Library to generate documentation
Home-page: https://github.com/Shchusia/gendoc
Author: Denis Shchutkiy
Author-email: denisshchutskyi@gmail.com
License: UNKNOWN
Keywords: pip,gen_doc
Platform: UNKNOWN
Requires-Python: >=3.7
License-File: LICENSE
Requires-Dist: astunparse (==1.6.3)
Requires-Dist: click (==8.1.2)
Requires-Dist: pydantic (==1.9.0)
Requires-Dist: PyYAML (==6.0)
